sinophone/__init__.py
sinophone/options.py
sinophone/utils.py
sinophone/phonetics/__init__.py
sinophone/phonetics/ipa_utils.py
sinophone/phonetics/phonetics.py
sinophone/phonology/__init__.py
sinophone/phonology/phonology.py
sinophone/phonology/syllable.py
sinophone-0.0.2.dist-info/LICENSE.txt
sinophone-0.0.2.dist-info/METADATA
sinophone-0.0.2.dist-info/WHEEL
sinophone-0.0.2.dist-info/top_level.txt
sinophone-0.0.2.dist-info/RECORD
