Metadata-Version: 2.1
Name: sinophone
Version: 0.0.2
Summary: Python package for manipulating Chinese phonology.
Home-page: https://github.com/wugniu/sinophone
Author: Yuanhao 'Nyoeghau' Chen
Author-email: nyoeghau@nyoeghau.com
License: MIT
Classifier: Development Status :: 3 - Alpha
Classifier: Intended Audience :: Science/Research
Classifier: Programming Language :: Python :: 3.8
Classifier: Programming Language :: Python :: 3.9
Classifier: Programming Language :: Python :: 3.10
License-File: LICENSE.txt
Requires-Dist: ipapy (==0.0.9)
